{"inkVersion":21,"root":[["^<i>You can hear Nessie before she comes into view of the desk, her lab coat swishing against the carpet.</i> ","#","^s You ","/#","#","^b 0 ","/#","#","^h 0 ","/#","#","^a 0 ","/#","#","^p 0","/#","\n","^“Finally, I have my plan!!” ","#","^s Nessie ","/#","#","^b 1 ","/#","#","^a 3 ","/#","#","^h 1 ","/#","#","^p 3","/#","\n","^<i>At last, maybe she can stop asking you for things you are unable to give her.</i> ","#","^s You","/#","\n","^“I am going to ask around to see if I can get any help, and then go swim in the lake anyways.” ","#","^s Nessie ","/#","#","^a 2 ","/#","#","^p 1","/#","\n","^“Things are a little desperate, so no harm in just trying, right?” ","#","^a 1 ","/#","#","^h 6","/#","\n","^<i>You are a little shocked at this brazen proposal. Didn’t she just mention not being able to swim very deep??<i/> ","#","^s You ","/#","#","^h 1","/#","\n","^<i>Regardless, you don’t want to deal with the legal fallout of a guest harming themselves on Motel property.</i>","\n","^<i>How are you going to stop her from doing this?</i>","\n","ev","str","^“There’s a monster in the lake.”","/str","/ev",{"*":"0.c-0","flg":20},"ev","str","^“It’s too dangerous!”","/str","/ev",{"*":"0.c-1","flg":20},{"c-0":["^ ",{"->":"monster"},"\n",{"->":"0.g-0"},{"#f":5}],"c-1":["^ ",{"->":"lakedanger"},"\n",{"->":"0.g-0"},{"#f":5}],"g-0":["done",{"#f":5}]}],"done",{"monster":["^<i>You realise far too late this was possibly the most insensitive thing you could have said. Massive failure. Catastrophic failure.</i> ","#","^s You ","/#","#","^minus 1 ","/#","#","^a 1 ","/#","#","^h 5 ","/#","#","^p 2","/#","\n","^Really?????? You think I haven’t heard that one before?” ","#","^s Nessie ","/#","#","^h 6 ","/#","#","^p 1","/#","\n","^“I thought you wanted to help me out, not insult me!” ","#","^a 3 ","/#","#","^h 3 ","/#","#","^p 3","/#","\n","^<i>You try to explain that you didn’t think the comment through, but the effort to convince her outweighs the result. The insult has already sunk in.</i> ","#","^s You ","/#","#","^a 1  ","/#","#","^h 5","/#","\n",{"->":"fuss"},{"#f":1}],"lakedanger":["^“Since when have calm, scenic lakes been a source of danger?\" ","#","^s Nessie ","/#","#","^plus 1 ","/#","#","^a 1 ","/#","#","^h 1 ","/#","#","^p 1","/#","\n","^\"Besides, I swam through there on my way in!” ","#","^a 3 ","/#","#","^h 2","/#","\n","^<i>Man, your logic wasn’t very sound for this argument.</i> ","#","^s You ","/#","#","^a 2","/#","\n","^“It’s nice of you to worry, but I can handle myself. It’ll just be a little tricky is all.” ","#","^s Nessie ","/#","#","^h 1 ","/#","#","^a 1","/#","\n",{"->":"fuss"},{"#f":1}],"fuss":[["^“I don’t know what all your fuss is about, considering I am literally part aquatic.” ","#","^s Nessie ","/#","#","^a 3 ","/#","#","^h 6 ","/#","#","^p 3","/#","\n","^<i>You realise your momentary panic about Motel health insurance and injury claims somewhat caused you to forget that your guest is a little more equipped for this scenario than another creature would be.</i> ","#","^s You","/#","\n","^“Go on, ask your questions, I can tell you are curious. Believe me, I get it all the time…” ","#","^s Nessie ","/#","#","^a 1 ","/#","#","^h 1 ","/#","#","^p 1","/#","\n","ev","str","^<i>Ask an uneducated question.</i>","/str","/ev",{"*":".^.c-0","flg":20},"ev","str","^<i>Back down.</i>","/str","/ev",{"*":".^.c-1","flg":20},{"c-0":["^ ",{"->":"scales"},"\n",{"#f":5}],"c-1":["^ ",{"->":"bepolite"},"\n",{"#f":5}]}],{"#f":1}],"scales":["^<i>You try your very best to think of something smart to ask her, something impressive.</i> ","#","^s You ","/#","#","^minus 1","/#","\n","^“So… you have any scales?”","\n","^“Huh?” ","#","^s Nessie ","/#","#","^a 2 ","/#","#","^h 3 ","/#","#","^p 1","/#","\n","^<i>She looks stunned, but hopefully not offended…</i> ","#","^s You","/#","\n","^“I know I said I was reptilian but not like <i>that</i>, silly!!” ","#","^s Nessie ","/#","#","^h 1 ","/#","#","^a 3 ","/#","#","^p 3","/#","\n","^“Honestly I don’t know why they don’t educate people on these things in school…” ","#","^a 1 ","/#","#","^p 2 ","/#","#","^h 5","/#","\n","^<i>Nessie seems bemused, but doesn’t explain further. I guess some things you will never get answers to.</i> ","#","^s You ","/#","#","^h 6 ","/#","#","^p 1","/#","\n",{"->":"toofamiliar"},{"#f":1}],"bepolite":["^<i>You feel too shy, simply opting to shrug and mumble a vague statement instead.</i> ","#","^s You ","/#","#","^plus 1","/#","\n","^“I know it’s a bit scary to ask, don’t worry!\" ","#","^s Nessie ","/#","#","^a 2 ","/#","#","^h 2 ","/#","#","^a 2","/#","\n","^\"I can totally tell you I am able to slightly breathe underwater, for a short time.” ","#","^h 1","/#","\n","^“Also I get dehydrated very quickly and can’t deal with cold temperatures! I could go on, but I don’t want to scare you off with too many facts.” ","#","^a 3","/#","\n","^<i>You’re grateful for the quick save. Plus, a few queries were answered for you.</i> ","#","^s You ","/#","#","^a 1","/#","\n",{"->":"toofamiliar"},{"#f":1}],"toofamiliar":["^“At least we got that awkwardness out of the way! Now we can move on to the honeymoon stage.” ","#","^s Nessie ","/#","#","^a 3 ","/#","#","^h 2 ","/#","#","^p 1","/#","\n","^<i>The what now!?-</i> ","#","^s You","/#","\n","^<i>If this is her idea of getting to know someone, you suppose being overly confident is one way to go about it… You laugh awkwardly.</i>","\n","^“Just kidding! I do feel like I’ve gotten to know you a bit now though.” ","#","^s Nessie ","/#","#","^a 1 ","/#","#","^a 3 ","/#","#","^h 1","/#","\n","^“My problem is far from solved, so I’m sure we’ll meet again very soon!!” ","#","^a 1","/#","\n","^“I’m gonna go ask around for flippers……” ","#","^h 6 ","/#","#","^p 2","/#","\n","^<i>You really do hope she manages to heave better luck with the guests than you.</i> ","#","^s You ","/#","#","^b 0 ","/#","#","^h 0 ","/#","#","^a 0 ","/#","#","^p 0","/#","\n","^<i>Looking back at your computer fills you with a sense of guilt. Maybe you can sort something out. Maybe…</i>","\n","end",{"#f":1}],"#f":1}],"listDefs":{}}